[{"uuid":"c60cce47-016c-43f8-8f1c-40c7e9a12876","firstName":"Brendan","lastName":"Viscount","fullName":"Brendan Viscount","salary":80000,"age":23,"jobTitle":"Developer","email":"bviscount@yahoo.com","contractHireDate":"2025-12-06T00:00:00Z","contractTerminationDate":null,"active":true},{"uuid":"550e8400-e29b-41d4-a716-446655440001","firstName":"Jane","lastName":"Doe","fullName":"Jane Doe","salary":85000,"age":28,"jobTitle":"Product Manager","email":"jane.doe@example.com","contractHireDate":"2019-06-01T00:00:00Z","contractTerminationDate":null,"active":true},{"uuid":"550e8400-e29b-41d4-a716-446655440000","firstName":"John","lastName":"Smith","fullName":"John Smith","salary":75000,"age":35,"jobTitle":"Software Engineer","email":"john.smith@example.com","contractHireDate":"2020-01-15T00:00:00Z","contractTerminationDate":null,"active":true},{"uuid":"1a13ecbe-4b34-43ae-bb40-0fded3b41358","firstName":"BatchTest","lastName":null,"fullName":"BatchTest","salary":null,"age":null,"jobTitle":null,"email":"batch@test.com","contractHireDate":"2025-12-06T22:55:46.061849600Z","contractTerminationDate":null,"active":true},{"uuid":"550e8400-e29b-41d4-a716-446655440002","firstName":"Bob","lastName":"Johnson","fullName":"Bob Johnson","salary":65000,"age":42,"jobTitle":"QA Engineer","email":"bob.johnson@example.com","contractHireDate":"2018-03-10T00:00:00Z","contractTerminationDate":"2022-12-31T00:00:00Z","active":false},{"uuid":"39b3b0e7-2bcd-49bf-af36-6ee2bdbeecb4","firstName":"Bob","lastName":null,"fullName":"Bob","salary":null,"age":null,"jobTitle":null,"email":"bob@example.com","contractHireDate":"2024-01-15T00:00:00Z","contractTerminationDate":null,"active":true},{"uuid":"94c4183f-6072-4a24-ab8c-72c633c4970c","firstName":"Alice","lastName":"Johnson","fullName":"Alice Johnson","salary":85000,"age":28,"jobTitle":"Software Engineer","email":"alice.johnson@example.com","contractHireDate":"2025-12-06T22:50:47.223225100Z","contractTerminationDate":null,"active":true}]